MANIFEST.in
setup.py
pyformulas/__init__.py
pyformulas.egg-info/PKG-INFO
pyformulas.egg-info/SOURCES.txt
pyformulas.egg-info/dependency_links.txt
pyformulas.egg-info/requires.txt
pyformulas.egg-info/top_level.txt
pyformulas/_formulas/discrete_search.py
pyformulas/_formulas/download.py
pyformulas/_formulas/plot.py
pyformulas/_formulas/screen.py
pyformulas/_formulas/settimeout.py
pyformulas/_formulas/thread.py
pyformulas/_formulas/__pycache__/discrete_search.cpython-36.pyc
pyformulas/_formulas/__pycache__/download.cpython-36.pyc
pyformulas/_formulas/__pycache__/plot.cpython-36.pyc
pyformulas/_formulas/__pycache__/screen.cpython-36.pyc
pyformulas/_formulas/__pycache__/settimeout.cpython-36.pyc
pyformulas/_formulas/__pycache__/thread.cpython-36.pyc
pyformulas/_formulas/audio/play.py
pyformulas/_formulas/audio/__pycache__/play.cpython-36.pyc
pyformulas/_formulas/net/Stream.py
pyformulas/_formulas/net/__pycache__/Stream.cpython-36.pyc