Metadata-Version: 1.2
Name: pyformulas
Version: 0.2.11
Summary: A library of ready-to-go Python formulas
Home-page: https://github.com/pyformulas/pyformulas
Author: pyformulas
Author-email: pyformulas@gmail.com
License: UNKNOWN
Keywords: python,formulas,recipes,cookbook,lazy,easy,quick,shortcut
Platform: UNKNOWN
Requires-Python: >=3.0
